Metadata-Version: 2.1
Name: fenix-checker
Version: 0.1.4
Summary: A small server which checks if user's IP is in a trusted Fenix network.
Home-page: https://gitlab.nic.cz/websites/fenix-checker
Author: Jiri Helebrant
Author-email: jiri.helebrant@nic.cz
License: UNKNOWN
Keywords: fenix
Platform: UNKNOWN
Classifier: Development Status :: 4 - Beta
Classifier: Programming Language :: Python
Classifier: Programming Language :: Python :: 3
Classifier: License :: OSI Approved :: GNU General Public License v3 (GPLv3)
Classifier: Operating System :: OS Independent
Requires-Python: >=3.6
